magboltz_gui/__init__.py
magboltz_gui/main.py
magboltz_gui/data/__init__.py
magboltz_gui/data/database.py
magboltz_gui/data/input_cards.py
magboltz_gui/generated/ui_export.py
magboltz_gui/generated/ui_export.pyi
magboltz_gui/generated/ui_main.py
magboltz_gui/generated/ui_main.pyi
magboltz_gui/generated/ui_preferences.py
magboltz_gui/generated/ui_preferences.pyi
magboltz_gui/generated/ui_search.py
magboltz_gui/generated/ui_search.pyi
magboltz_gui/icons/icon-192x192.png
magboltz_gui/icons/icon.svg
magboltz_gui/tool/__init__.py
magboltz_gui/tool/gen_ui.py
magboltz_gui/tool/ui2stub.py
magboltz_gui/ui/export.ui
magboltz_gui/ui/main.ui
magboltz_gui/ui/preferences.ui
magboltz_gui/ui/search.ui
magboltz_gui/util/__init__.py
magboltz_gui/util/parser.py
magboltz_gui/util/platform.py
magboltz_gui/util/process.py
magboltz_gui/window/__init__.py
magboltz_gui/window/delegates.py
magboltz_gui/window/export_window.py
magboltz_gui/window/gas_pie_widget.py
magboltz_gui/window/main_window.py
magboltz_gui/window/search_window.py
magboltz_gui-0.2.1.dist-info/METADATA
magboltz_gui-0.2.1.dist-info/WHEEL
magboltz_gui-0.2.1.dist-info/entry_points.txt
magboltz_gui-0.2.1.dist-info/top_level.txt
magboltz_gui-0.2.1.dist-info/RECORD
