Metadata-Version: 2.4
Name: magboltz-gui
Version: 0.2.1
Summary: Magboltz GUI - a GUI for Magboltz
Author-email: Michele Renda <michele.renda@cern.ch>, Dan Andrei Ciubotaru <dan.andrei.ciubotaru@cern.ch>
Project-URL: Homepage, https://gitlab.com/micrenda/magboltz-gui
Project-URL: Documentation, https://gitlab.com/micrenda/magboltz-gui
Project-URL: Source, https://gitlab.com/micrenda/magboltz-gui
Project-URL: Tracker, https://gitlab.com/micrenda/magboltz-gui/issues
Requires-Python: >=3.11
Requires-Dist: matplotlib>=3.10.7
Requires-Dist: typing-extensions>=4.15.0
Provides-Extra: qt
Requires-Dist: PyQt6>=6.9.1; extra == "qt"
Requires-Dist: PyQt6-Qt6>=6.9.1; extra == "qt"
Requires-Dist: pyqt6-utils>=0.5.0; extra == "qt"
